takeout/__init__.py
takeout/takeout.py
takeout.py-1.3.1.dist-info/LICENSE
takeout.py-1.3.1.dist-info/METADATA
takeout.py-1.3.1.dist-info/WHEEL
takeout.py-1.3.1.dist-info/top_level.txt
takeout.py-1.3.1.dist-info/RECORD
