Metadata-Version: 2.1
Name: takeout.py
Version: 1.3.1
Summary: A Takeout client for Python.
Home-page: https://github.com/Takeout-bysourfruit/takeout.py
Author: Takeout by Sourfruit
Author-email: <hello@def-not-hacking-the.net>
License: UNKNOWN
Keywords: python,takeout.py,takeout,sourfruit
Platform: UNKNOWN
License-File: LICENSE
Requires-Dist: requests
Requires-Dist: certifi
